{
 "custom_fields": [
  {
   "_assign": null,
   "_comments": null,
   "_liked_by": null,
   "_user_tags": null,
   "allow_in_quick_entry": 0,
   "allow_on_submit": 0,
   "bold": 0,
   "collapsible": 0,
   "collapsible_depends_on": null,
   "columns": 0,
   "creation": "2025-01-07 10:14:49.963540",
   "default": null,
   "depends_on": null,
   "description": null,
   "docstatus": 0,
   "dt": "Supplier Quotation Item",
   "fetch_from": null,
   "fetch_if_empty": 0,
   "fieldname": "cb_gst_details",
   "fieldtype": "Column Break",
   "hidden": 0,
   "hide_border": 0,
   "hide_days": 0,
   "hide_seconds": 0,
   "idx": 0,
   "ignore_user_permissions": 0,
   "ignore_xss_filter": 0,
   "in_global_search": 0,
   "in_list_view": 0,
   "in_preview": 0,
   "in_standard_filter": 0,
   "insert_after": "cess_non_advol_rate",
   "is_system_generated": 1,
   "is_virtual": 0,
   "label": null,
   "length": 0,
   "link_filters": null,
   "mandatory_depends_on": null,
   "modified": "2025-01-07 10:14:49.963540",
   "modified_by": "Administrator",
   "module": null,
   "name": "Supplier Quotation Item-cb_gst_details",
   "no_copy": 0,
   "non_negative": 0,
   "options": null,
   "owner": "Administrator",
   "permlevel": 0,
   "placeholder": null,
   "precision": "",
   "print_hide": 0,
   "print_hide_if_no_value": 0,
   "print_width": null,
   "read_only": 0,
   "read_only_depends_on": null,
   "report_hide": 0,
   "reqd": 0,
   "search_index": 0,
   "show_dashboard": 0,
   "sort_options": 0,
   "translatable": 0,
   "unique": 0,
   "width": null
  },
  {
   "_assign": null,
   "_comments": null,
   "_liked_by": null,
   "_user_tags": null,
   "allow_in_quick_entry": 0,
   "allow_on_submit": 0,
   "bold": 0,
   "collapsible": 0,
   "collapsible_depends_on": null,
   "columns": 0,
   "creation": "2025-01-07 10:14:49.970286",
   "default": null,
   "depends_on": null,
   "description": null,
   "docstatus": 0,
   "dt": "Supplier Quotation Item",
   "fetch_from": null,
   "fetch_if_empty": 0,
   "fieldname": "cess_amount",
   "fieldtype": "Currency",
   "hidden": 0,
   "hide_border": 0,
   "hide_days": 0,
   "hide_seconds": 0,
   "idx": 0,
   "ignore_user_permissions": 0,
   "ignore_xss_filter": 0,
   "in_global_search": 0,
   "in_list_view": 0,
   "in_preview": 0,
   "in_standard_filter": 0,
   "insert_after": "sgst_amount",
   "is_system_generated": 1,
   "is_virtual": 0,
   "label": "CESS Amount",
   "length": 0,
   "link_filters": null,
   "mandatory_depends_on": null,
   "modified": "2025-01-07 10:14:49.970286",
   "modified_by": "Administrator",
   "module": null,
   "name": "Supplier Quotation Item-cess_amount",
   "no_copy": 1,
   "non_negative": 0,
   "options": "Company:company:default_currency",
   "owner": "Administrator",
   "permlevel": 0,
   "placeholder": null,
   "precision": "",
   "print_hide": 0,
   "print_hide_if_no_value": 0,
   "print_width": null,
   "read_only": 1,
   "read_only_depends_on": null,
   "report_hide": 0,
   "reqd": 0,
   "search_index": 0,
   "show_dashboard": 0,
   "sort_options": 0,
   "translatable": 0,
   "unique": 0,
   "width": null
  },
  {
   "_assign": null,
   "_comments": null,
   "_liked_by": null,
   "_user_tags": null,
   "allow_in_quick_entry": 0,
   "allow_on_submit": 0,
   "bold": 0,
   "collapsible": 0,
   "collapsible_depends_on": null,
   "columns": 0,
   "creation": "2025-01-07 10:14:49.971968",
   "default": null,
   "depends_on": null,
   "description": null,
   "docstatus": 0,
   "dt": "Supplier Quotation Item",
   "fetch_from": null,
   "fetch_if_empty": 0,
   "fieldname": "cess_non_advol_amount",
   "fieldtype": "Currency",
   "hidden": 0,
   "hide_border": 0,
   "hide_days": 0,
   "hide_seconds": 0,
   "idx": 0,
   "ignore_user_permissions": 0,
   "ignore_xss_filter": 0,
   "in_global_search": 0,
   "in_list_view": 0,
   "in_preview": 0,
   "in_standard_filter": 0,
   "insert_after": "cess_amount",
   "is_system_generated": 1,
   "is_virtual": 0,
   "label": "CESS Non Advol Amount",
   "length": 0,
   "link_filters": null,
   "mandatory_depends_on": null,
   "modified": "2025-01-07 10:14:49.971968",
   "modified_by": "Administrator",
   "module": null,
   "name": "Supplier Quotation Item-cess_non_advol_amount",
   "no_copy": 1,
   "non_negative": 0,
   "options": "Company:company:default_currency",
   "owner": "Administrator",
   "permlevel": 0,
   "placeholder": null,
   "precision": "",
   "print_hide": 0,
   "print_hide_if_no_value": 0,
   "print_width": null,
   "read_only": 1,
   "read_only_depends_on": null,
   "report_hide": 0,
   "reqd": 0,
   "search_index": 0,
   "show_dashboard": 0,
   "sort_options": 0,
   "translatable": 0,
   "unique": 0,
   "width": null
  },
  {
   "_assign": null,
   "_comments": null,
   "_liked_by": null,
   "_user_tags": null,
   "allow_in_quick_entry": 0,
   "allow_on_submit": 0,
   "bold": 0,
   "collapsible": 0,
   "collapsible_depends_on": null,
   "columns": 0,
   "creation": "2025-01-07 10:14:49.961870",
   "default": null,
   "depends_on": null,
   "description": null,
   "docstatus": 0,
   "dt": "Supplier Quotation Item",
   "fetch_from": null,
   "fetch_if_empty": 0,
   "fieldname": "cess_non_advol_rate",
   "fieldtype": "Float",
   "hidden": 0,
   "hide_border": 0,
   "hide_days": 0,
   "hide_seconds": 0,
   "idx": 0,
   "ignore_user_permissions": 0,
   "ignore_xss_filter": 0,
   "in_global_search": 0,
   "in_list_view": 0,
   "in_preview": 0,
   "in_standard_filter": 0,
   "insert_after": "cess_rate",
   "is_system_generated": 1,
   "is_virtual": 0,
   "label": "CESS Non Advol Rate",
   "length": 0,
   "link_filters": null,
   "mandatory_depends_on": null,
   "modified": "2025-01-07 10:14:49.961870",
   "modified_by": "Administrator",
   "module": null,
   "name": "Supplier Quotation Item-cess_non_advol_rate",
   "no_copy": 1,
   "non_negative": 0,
   "options": null,
   "owner": "Administrator",
   "permlevel": 0,
   "placeholder": null,
   "precision": "",
   "print_hide": 0,
   "print_hide_if_no_value": 0,
   "print_width": null,
   "read_only": 1,
   "read_only_depends_on": null,
   "report_hide": 0,
   "reqd": 0,
   "search_index": 0,
   "show_dashboard": 0,
   "sort_options": 0,
   "translatable": 0,
   "unique": 0,
   "width": null
  },
  {
   "_assign": null,
   "_comments": null,
   "_liked_by": null,
   "_user_tags": null,
   "allow_in_quick_entry": 0,
   "allow_on_submit": 0,
   "bold": 0,
   "collapsible": 0,
   "collapsible_depends_on": null,
   "columns": 0,
   "creation": "2025-01-07 10:14:49.960227",
   "default": null,
   "depends_on": null,
   "description": null,
   "docstatus": 0,
   "dt": "Supplier Quotation Item",
   "fetch_from": null,
   "fetch_if_empty": 0,
   "fieldname": "cess_rate",
   "fieldtype": "Float",
   "hidden": 0,
   "hide_border": 0,
   "hide_days": 0,
   "hide_seconds": 0,
   "idx": 0,
   "ignore_user_permissions": 0,
   "ignore_xss_filter": 0,
   "in_global_search": 0,
   "in_list_view": 0,
   "in_preview": 0,
   "in_standard_filter": 0,
   "insert_after": "sgst_rate",
   "is_system_generated": 1,
   "is_virtual": 0,
   "label": "CESS Rate",
   "length": 0,
   "link_filters": null,
   "mandatory_depends_on": null,
   "modified": "2025-01-07 10:14:49.960227",
   "modified_by": "Administrator",
   "module": null,
   "name": "Supplier Quotation Item-cess_rate",
   "no_copy": 1,
   "non_negative": 0,
   "options": null,
   "owner": "Administrator",
   "permlevel": 0,
   "placeholder": null,
   "precision": "",
   "print_hide": 0,
   "print_hide_if_no_value": 0,
   "print_width": null,
   "read_only": 1,
   "read_only_depends_on": null,
   "report_hide": 0,
   "reqd": 0,
   "search_index": 0,
   "show_dashboard": 0,
   "sort_options": 0,
   "translatable": 0,
   "unique": 0,
   "width": null
  },
  {
   "_assign": null,
   "_comments": null,
   "_liked_by": null,
   "_user_tags": null,
   "allow_in_quick_entry": 0,
   "allow_on_submit": 0,
   "bold": 0,
   "collapsible": 0,
   "collapsible_depends_on": null,
   "columns": 0,
   "creation": "2025-01-07 10:14:49.966942",
   "default": null,
   "depends_on": null,
   "description": null,
   "docstatus": 0,
   "dt": "Supplier Quotation Item",
   "fetch_from": null,
   "fetch_if_empty": 0,
   "fieldname": "cgst_amount",
   "fieldtype": "Currency",
   "hidden": 0,
   "hide_border": 0,
   "hide_days": 0,
   "hide_seconds": 0,
   "idx": 0,
   "ignore_user_permissions": 0,
   "ignore_xss_filter": 0,
   "in_global_search": 0,
   "in_list_view": 0,
   "in_preview": 0,
   "in_standard_filter": 0,
   "insert_after": "igst_amount",
   "is_system_generated": 1,
   "is_virtual": 0,
   "label": "CGST Amount",
   "length": 0,
   "link_filters": null,
   "mandatory_depends_on": null,
   "modified": "2025-01-07 10:14:49.966942",
   "modified_by": "Administrator",
   "module": null,
   "name": "Supplier Quotation Item-cgst_amount",
   "no_copy": 1,
   "non_negative": 0,
   "options": "Company:company:default_currency",
   "owner": "Administrator",
   "permlevel": 0,
   "placeholder": null,
   "precision": "",
   "print_hide": 0,
   "print_hide_if_no_value": 0,
   "print_width": null,
   "read_only": 1,
   "read_only_depends_on": null,
   "report_hide": 0,
   "reqd": 0,
   "search_index": 0,
   "show_dashboard": 0,
   "sort_options": 0,
   "translatable": 0,
   "unique": 0,
   "width": null
  },
  {
   "_assign": null,
   "_comments": null,
   "_liked_by": null,
   "_user_tags": null,
   "allow_in_quick_entry": 0,
   "allow_on_submit": 0,
   "bold": 0,
   "collapsible": 0,
   "collapsible_depends_on": null,
   "columns": 0,
   "creation": "2025-01-07 10:14:49.956967",
   "default": null,
   "depends_on": null,
   "description": null,
   "docstatus": 0,
   "dt": "Supplier Quotation Item",
   "fetch_from": null,
   "fetch_if_empty": 0,
   "fieldname": "cgst_rate",
   "fieldtype": "Float",
   "hidden": 0,
   "hide_border": 0,
   "hide_days": 0,
   "hide_seconds": 0,
   "idx": 0,
   "ignore_user_permissions": 0,
   "ignore_xss_filter": 0,
   "in_global_search": 0,
   "in_list_view": 0,
   "in_preview": 0,
   "in_standard_filter": 0,
   "insert_after": "igst_rate",
   "is_system_generated": 1,
   "is_virtual": 0,
   "label": "CGST Rate",
   "length": 0,
   "link_filters": null,
   "mandatory_depends_on": null,
   "modified": "2025-01-07 10:14:49.956967",
   "modified_by": "Administrator",
   "module": null,
   "name": "Supplier Quotation Item-cgst_rate",
   "no_copy": 1,
   "non_negative": 0,
   "options": null,
   "owner": "Administrator",
   "permlevel": 0,
   "placeholder": null,
   "precision": "",
   "print_hide": 0,
   "print_hide_if_no_value": 0,
   "print_width": null,
   "read_only": 1,
   "read_only_depends_on": null,
   "report_hide": 0,
   "reqd": 0,
   "search_index": 0,
   "show_dashboard": 0,
   "sort_options": 0,
   "translatable": 0,
   "unique": 0,
   "width": null
  },
  {
   "_assign": null,
   "_comments": null,
   "_liked_by": null,
   "_user_tags": null,
   "allow_in_quick_entry": 0,
   "allow_on_submit": 0,
   "bold": 0,
   "collapsible": 0,
   "collapsible_depends_on": null,
   "columns": 0,
   "creation": "2025-04-26 11:07:18.950432",
   "default": null,
   "depends_on": null,
   "description": null,
   "docstatus": 0,
   "dt": "Supplier Quotation Item",
   "fetch_from": null,
   "fetch_if_empty": 0,
   "fieldname": "custom_drawing_no",
   "fieldtype": "Data",
   "hidden": 0,
   "hide_border": 0,
   "hide_days": 0,
   "hide_seconds": 0,
   "idx": 13,
   "ignore_user_permissions": 0,
   "ignore_xss_filter": 0,
   "in_global_search": 0,
   "in_list_view": 0,
   "in_preview": 0,
   "in_standard_filter": 0,
   "insert_after": "brand",
   "is_system_generated": 0,
   "is_virtual": 0,
   "label": "Drawing No",
   "length": 0,
   "link_filters": null,
   "mandatory_depends_on": null,
   "modified": "2025-04-26 11:07:18.950432",
   "modified_by": "Administrator",
   "module": null,
   "name": "Supplier Quotation Item-custom_drawing_no",
   "no_copy": 0,
   "non_negative": 0,
   "options": null,
   "owner": "Administrator",
   "permlevel": 0,
   "placeholder": null,
   "precision": "",
   "print_hide": 0,
   "print_hide_if_no_value": 0,
   "print_width": null,
   "read_only": 0,
   "read_only_depends_on": null,
   "report_hide": 0,
   "reqd": 0,
   "search_index": 0,
   "show_dashboard": 0,
   "sort_options": 0,
   "translatable": 1,
   "unique": 0,
   "width": null
  },
  {
   "_assign": null,
   "_comments": null,
   "_liked_by": null,
   "_user_tags": null,
   "allow_in_quick_entry": 0,
   "allow_on_submit": 0,
   "bold": 0,
   "collapsible": 1,
   "collapsible_depends_on": null,
   "columns": 0,
   "creation": "2025-01-07 10:14:49.953678",
   "default": null,
   "depends_on": null,
   "description": null,
   "docstatus": 0,
   "dt": "Supplier Quotation Item",
   "fetch_from": null,
   "fetch_if_empty": 0,
   "fieldname": "gst_details_section",
   "fieldtype": "Section Break",
   "hidden": 0,
   "hide_border": 0,
   "hide_days": 0,
   "hide_seconds": 0,
   "idx": 0,
   "ignore_user_permissions": 0,
   "ignore_xss_filter": 0,
   "in_global_search": 0,
   "in_list_view": 0,
   "in_preview": 0,
   "in_standard_filter": 0,
   "insert_after": "taxable_value",
   "is_system_generated": 1,
   "is_virtual": 0,
   "label": "GST Details",
   "length": 0,
   "link_filters": null,
   "mandatory_depends_on": null,
   "modified": "2025-01-07 10:14:49.953678",
   "modified_by": "Administrator",
   "module": null,
   "name": "Supplier Quotation Item-gst_details_section",
   "no_copy": 0,
   "non_negative": 0,
   "options": null,
   "owner": "Administrator",
   "permlevel": 0,
   "placeholder": null,
   "precision": "",
   "print_hide": 0,
   "print_hide_if_no_value": 0,
   "print_width": null,
   "read_only": 0,
   "read_only_depends_on": null,
   "report_hide": 0,
   "reqd": 0,
   "search_index": 0,
   "show_dashboard": 0,
   "sort_options": 0,
   "translatable": 0,
   "unique": 0,
   "width": null
  },
  {
   "_assign": null,
   "_comments": null,
   "_liked_by": null,
   "_user_tags": null,
   "allow_in_quick_entry": 0,
   "allow_on_submit": 1,
   "bold": 0,
   "collapsible": 0,
   "collapsible_depends_on": null,
   "columns": 0,
   "creation": "2025-01-07 10:14:49.950399",
   "default": null,
   "depends_on": null,
   "description": null,
   "docstatus": 0,
   "dt": "Supplier Quotation Item",
   "fetch_from": "item_code.gst_hsn_code",
   "fetch_if_empty": 1,
   "fieldname": "gst_hsn_code",
   "fieldtype": "Data",
   "hidden": 0,
   "hide_border": 0,
   "hide_days": 0,
   "hide_seconds": 0,
   "idx": 0,
   "ignore_user_permissions": 0,
   "ignore_xss_filter": 0,
   "in_global_search": 0,
   "in_list_view": 0,
   "in_preview": 0,
   "in_standard_filter": 0,
   "insert_after": "description",
   "is_system_generated": 1,
   "is_virtual": 0,
   "label": "HSN/SAC",
   "length": 0,
   "link_filters": null,
   "mandatory_depends_on": null,
   "modified": "2025-01-07 10:14:49.950399",
   "modified_by": "Administrator",
   "module": null,
   "name": "Supplier Quotation Item-gst_hsn_code",
   "no_copy": 0,
   "non_negative": 0,
   "options": null,
   "owner": "Administrator",
   "permlevel": 0,
   "placeholder": null,
   "precision": "",
   "print_hide": 1,
   "print_hide_if_no_value": 0,
   "print_width": null,
   "read_only": 0,
   "read_only_depends_on": null,
   "report_hide": 0,
   "reqd": 0,
   "search_index": 0,
   "show_dashboard": 0,
   "sort_options": 0,
   "translatable": 0,
   "unique": 0,
   "width": null
  },
  {
   "_assign": null,
   "_comments": null,
   "_liked_by": null,
   "_user_tags": null,
   "allow_in_quick_entry": 0,
   "allow_on_submit": 0,
   "bold": 0,
   "collapsible": 0,
   "collapsible_depends_on": null,
   "columns": 0,
   "creation": "2025-01-07 10:14:49.952016",
   "default": null,
   "depends_on": null,
   "description": null,
   "docstatus": 0,
   "dt": "Supplier Quotation Item",
   "fetch_from": "item_tax_template.gst_treatment",
   "fetch_if_empty": 1,
   "fieldname": "gst_treatment",
   "fieldtype": "Autocomplete",
   "hidden": 0,
   "hide_border": 0,
   "hide_days": 0,
   "hide_seconds": 0,
   "idx": 0,
   "ignore_user_permissions": 0,
   "ignore_xss_filter": 0,
   "in_global_search": 0,
   "in_list_view": 0,
   "in_preview": 0,
   "in_standard_filter": 0,
   "insert_after": "item_tax_template",
   "is_system_generated": 1,
   "is_virtual": 0,
   "label": "GST Treatment",
   "length": 0,
   "link_filters": null,
   "mandatory_depends_on": null,
   "modified": "2025-01-07 10:14:49.952016",
   "modified_by": "Administrator",
   "module": null,
   "name": "Supplier Quotation Item-gst_treatment",
   "no_copy": 1,
   "non_negative": 0,
   "options": "Taxable\nZero-Rated\nNil-Rated\nExempted\nNon-GST",
   "owner": "Administrator",
   "permlevel": 0,
   "placeholder": null,
   "precision": "",
   "print_hide": 1,
   "print_hide_if_no_value": 0,
   "print_width": null,
   "read_only": 1,
   "read_only_depends_on": null,
   "report_hide": 0,
   "reqd": 0,
   "search_index": 0,
   "show_dashboard": 0,
   "sort_options": 0,
   "translatable": 0,
   "unique": 0,
   "width": null
  },
  {
   "_assign": null,
   "_comments": null,
   "_liked_by": null,
   "_user_tags": null,
   "allow_in_quick_entry": 0,
   "allow_on_submit": 0,
   "bold": 0,
   "collapsible": 0,
   "collapsible_depends_on": null,
   "columns": 0,
   "creation": "2025-01-07 10:14:49.965215",
   "default": null,
   "depends_on": null,
   "description": null,
   "docstatus": 0,
   "dt": "Supplier Quotation Item",
   "fetch_from": null,
   "fetch_if_empty": 0,
   "fieldname": "igst_amount",
   "fieldtype": "Currency",
   "hidden": 0,
   "hide_border": 0,
   "hide_days": 0,
   "hide_seconds": 0,
   "idx": 0,
   "ignore_user_permissions": 0,
   "ignore_xss_filter": 0,
   "in_global_search": 0,
   "in_list_view": 0,
   "in_preview": 0,
   "in_standard_filter": 0,
   "insert_after": "cb_gst_details",
   "is_system_generated": 1,
   "is_virtual": 0,
   "label": "IGST Amount",
   "length": 0,
   "link_filters": null,
   "mandatory_depends_on": null,
   "modified": "2025-01-07 10:14:49.965215",
   "modified_by": "Administrator",
   "module": null,
   "name": "Supplier Quotation Item-igst_amount",
   "no_copy": 1,
   "non_negative": 0,
   "options": "Company:company:default_currency",
   "owner": "Administrator",
   "permlevel": 0,
   "placeholder": null,
   "precision": "",
   "print_hide": 0,
   "print_hide_if_no_value": 0,
   "print_width": null,
   "read_only": 1,
   "read_only_depends_on": null,
   "report_hide": 0,
   "reqd": 0,
   "search_index": 0,
   "show_dashboard": 0,
   "sort_options": 0,
   "translatable": 0,
   "unique": 0,
   "width": null
  },
  {
   "_assign": null,
   "_comments": null,
   "_liked_by": null,
   "_user_tags": null,
   "allow_in_quick_entry": 0,
   "allow_on_submit": 0,
   "bold": 0,
   "collapsible": 0,
   "collapsible_depends_on": null,
   "columns": 0,
   "creation": "2025-01-07 10:14:49.955327",
   "default": null,
   "depends_on": null,
   "description": null,
   "docstatus": 0,
   "dt": "Supplier Quotation Item",
   "fetch_from": null,
   "fetch_if_empty": 0,
   "fieldname": "igst_rate",
   "fieldtype": "Float",
   "hidden": 0,
   "hide_border": 0,
   "hide_days": 0,
   "hide_seconds": 0,
   "idx": 0,
   "ignore_user_permissions": 0,
   "ignore_xss_filter": 0,
   "in_global_search": 0,
   "in_list_view": 0,
   "in_preview": 0,
   "in_standard_filter": 0,
   "insert_after": "gst_details_section",
   "is_system_generated": 1,
   "is_virtual": 0,
   "label": "IGST Rate",
   "length": 0,
   "link_filters": null,
   "mandatory_depends_on": null,
   "modified": "2025-01-07 10:14:49.955327",
   "modified_by": "Administrator",
   "module": null,
   "name": "Supplier Quotation Item-igst_rate",
   "no_copy": 1,
   "non_negative": 0,
   "options": null,
   "owner": "Administrator",
   "permlevel": 0,
   "placeholder": null,
   "precision": "",
   "print_hide": 0,
   "print_hide_if_no_value": 0,
   "print_width": null,
   "read_only": 1,
   "read_only_depends_on": null,
   "report_hide": 0,
   "reqd": 0,
   "search_index": 0,
   "show_dashboard": 0,
   "sort_options": 0,
   "translatable": 0,
   "unique": 0,
   "width": null
  },
  {
   "_assign": null,
   "_comments": null,
   "_liked_by": null,
   "_user_tags": null,
   "allow_in_quick_entry": 0,
   "allow_on_submit": 0,
   "bold": 0,
   "collapsible": 0,
   "collapsible_depends_on": null,
   "columns": 0,
   "creation": "2025-01-07 10:14:50.354417",
   "default": null,
   "depends_on": null,
   "description": null,
   "docstatus": 0,
   "dt": "Supplier Quotation Item",
   "fetch_from": "item_code.is_ineligible_for_itc",
   "fetch_if_empty": 1,
   "fieldname": "is_ineligible_for_itc",
   "fieldtype": "Check",
   "hidden": 0,
   "hide_border": 0,
   "hide_days": 0,
   "hide_seconds": 0,
   "idx": 0,
   "ignore_user_permissions": 0,
   "ignore_xss_filter": 0,
   "in_global_search": 0,
   "in_list_view": 0,
   "in_preview": 0,
   "in_standard_filter": 0,
   "insert_after": "gst_hsn_code",
   "is_system_generated": 1,
   "is_virtual": 0,
   "label": "Is Ineligible for Input Tax Credit",
   "length": 0,
   "link_filters": null,
   "mandatory_depends_on": null,
   "modified": "2025-01-07 10:14:50.354417",
   "modified_by": "Administrator",
   "module": null,
   "name": "Supplier Quotation Item-is_ineligible_for_itc",
   "no_copy": 0,
   "non_negative": 0,
   "options": null,
   "owner": "Administrator",
   "permlevel": 0,
   "placeholder": null,
   "precision": "",
   "print_hide": 1,
   "print_hide_if_no_value": 0,
   "print_width": null,
   "read_only": 0,
   "read_only_depends_on": null,
   "report_hide": 0,
   "reqd": 0,
   "search_index": 0,
   "show_dashboard": 0,
   "sort_options": 0,
   "translatable": 0,
   "unique": 0,
   "width": null
  },
  {
   "_assign": null,
   "_comments": null,
   "_liked_by": null,
   "_user_tags": null,
   "allow_in_quick_entry": 0,
   "allow_on_submit": 0,
   "bold": 0,
   "collapsible": 0,
   "collapsible_depends_on": null,
   "columns": 0,
   "creation": "2025-01-07 10:14:49.968610",
   "default": null,
   "depends_on": null,
   "description": null,
   "docstatus": 0,
   "dt": "Supplier Quotation Item",
   "fetch_from": null,
   "fetch_if_empty": 0,
   "fieldname": "sgst_amount",
   "fieldtype": "Currency",
   "hidden": 0,
   "hide_border": 0,
   "hide_days": 0,
   "hide_seconds": 0,
   "idx": 0,
   "ignore_user_permissions": 0,
   "ignore_xss_filter": 0,
   "in_global_search": 0,
   "in_list_view": 0,
   "in_preview": 0,
   "in_standard_filter": 0,
   "insert_after": "cgst_amount",
   "is_system_generated": 1,
   "is_virtual": 0,
   "label": "SGST Amount",
   "length": 0,
   "link_filters": null,
   "mandatory_depends_on": null,
   "modified": "2025-01-07 10:14:49.968610",
   "modified_by": "Administrator",
   "module": null,
   "name": "Supplier Quotation Item-sgst_amount",
   "no_copy": 1,
   "non_negative": 0,
   "options": "Company:company:default_currency",
   "owner": "Administrator",
   "permlevel": 0,
   "placeholder": null,
   "precision": "",
   "print_hide": 0,
   "print_hide_if_no_value": 0,
   "print_width": null,
   "read_only": 1,
   "read_only_depends_on": null,
   "report_hide": 0,
   "reqd": 0,
   "search_index": 0,
   "show_dashboard": 0,
   "sort_options": 0,
   "translatable": 0,
   "unique": 0,
   "width": null
  },
  {
   "_assign": null,
   "_comments": null,
   "_liked_by": null,
   "_user_tags": null,
   "allow_in_quick_entry": 0,
   "allow_on_submit": 0,
   "bold": 0,
   "collapsible": 0,
   "collapsible_depends_on": null,
   "columns": 0,
   "creation": "2025-01-07 10:14:49.958604",
   "default": null,
   "depends_on": null,
   "description": null,
   "docstatus": 0,
   "dt": "Supplier Quotation Item",
   "fetch_from": null,
   "fetch_if_empty": 0,
   "fieldname": "sgst_rate",
   "fieldtype": "Float",
   "hidden": 0,
   "hide_border": 0,
   "hide_days": 0,
   "hide_seconds": 0,
   "idx": 0,
   "ignore_user_permissions": 0,
   "ignore_xss_filter": 0,
   "in_global_search": 0,
   "in_list_view": 0,
   "in_preview": 0,
   "in_standard_filter": 0,
   "insert_after": "cgst_rate",
   "is_system_generated": 1,
   "is_virtual": 0,
   "label": "SGST Rate",
   "length": 0,
   "link_filters": null,
   "mandatory_depends_on": null,
   "modified": "2025-01-07 10:14:49.958604",
   "modified_by": "Administrator",
   "module": null,
   "name": "Supplier Quotation Item-sgst_rate",
   "no_copy": 1,
   "non_negative": 0,
   "options": null,
   "owner": "Administrator",
   "permlevel": 0,
   "placeholder": null,
   "precision": "",
   "print_hide": 0,
   "print_hide_if_no_value": 0,
   "print_width": null,
   "read_only": 1,
   "read_only_depends_on": null,
   "report_hide": 0,
   "reqd": 0,
   "search_index": 0,
   "show_dashboard": 0,
   "sort_options": 0,
   "translatable": 0,
   "unique": 0,
   "width": null
  },
  {
   "_assign": null,
   "_comments": null,
   "_liked_by": null,
   "_user_tags": null,
   "allow_in_quick_entry": 0,
   "allow_on_submit": 0,
   "bold": 0,
   "collapsible": 0,
   "collapsible_depends_on": null,
   "columns": 0,
   "creation": "2025-01-07 10:14:49.919955",
   "default": null,
   "depends_on": null,
   "description": null,
   "docstatus": 0,
   "dt": "Supplier Quotation Item",
   "fetch_from": null,
   "fetch_if_empty": 0,
   "fieldname": "taxable_value",
   "fieldtype": "Currency",
   "hidden": 0,
   "hide_border": 0,
   "hide_days": 0,
   "hide_seconds": 0,
   "idx": 0,
   "ignore_user_permissions": 0,
   "ignore_xss_filter": 0,
   "in_global_search": 0,
   "in_list_view": 0,
   "in_preview": 0,
   "in_standard_filter": 0,
   "insert_after": "base_net_amount",
   "is_system_generated": 1,
   "is_virtual": 0,
   "label": "Taxable Value",
   "length": 0,
   "link_filters": null,
   "mandatory_depends_on": null,
   "modified": "2025-01-07 10:14:49.919955",
   "modified_by": "Administrator",
   "module": null,
   "name": "Supplier Quotation Item-taxable_value",
   "no_copy": 1,
   "non_negative": 0,
   "options": "Company:company:default_currency",
   "owner": "Administrator",
   "permlevel": 0,
   "placeholder": null,
   "precision": "",
   "print_hide": 1,
   "print_hide_if_no_value": 0,
   "print_width": null,
   "read_only": 1,
   "read_only_depends_on": null,
   "report_hide": 0,
   "reqd": 0,
   "search_index": 0,
   "show_dashboard": 0,
   "sort_options": 0,
   "translatable": 0,
   "unique": 0,
   "width": null
  }
 ],
 "custom_perms": [],
 "doctype": "Supplier Quotation Item",
 "links": [],
 "property_setters": [
  {
   "_assign": null,
   "_comments": null,
   "_liked_by": null,
   "_user_tags": null,
   "creation": "2025-04-26 11:07:18.875450",
   "default_value": null,
   "doc_type": "Supplier Quotation Item",
   "docstatus": 0,
   "doctype_or_field": "DocType",
   "field_name": null,
   "idx": 0,
   "is_system_generated": 0,
   "modified": "2025-04-26 11:07:18.875450",
   "modified_by": "Administrator",
   "module": null,
   "name": "Supplier Quotation Item-main-field_order",
   "owner": "Administrator",
   "property": "field_order",
   "property_type": "Data",
   "row_name": null,
   "value": "[\"item_code\", \"supplier_part_no\", \"item_name\", \"column_break_3\", \"lead_time_days\", \"expected_delivery_date\", \"is_free_item\", \"section_break_5\", \"description\", \"gst_hsn_code\", \"is_ineligible_for_itc\", \"item_group\", \"brand\", \"drawing_no\", \"col_break1\", \"image\", \"image_view\", \"quantity_and_rate\", \"qty\", \"stock_uom\", \"col_break2\", \"uom\", \"conversion_factor\", \"stock_qty\", \"sec_break_price_list\", \"price_list_rate\", \"discount_percentage\", \"discount_amount\", \"col_break_price_list\", \"base_price_list_rate\", \"sec_break1\", \"rate\", \"amount\", \"item_tax_template\", \"gst_treatment\", \"col_break3\", \"base_rate\", \"base_amount\", \"pricing_rules\", \"section_break_24\", \"net_rate\", \"net_amount\", \"column_break_27\", \"base_net_rate\", \"base_net_amount\", \"taxable_value\", \"gst_details_section\", \"igst_rate\", \"cgst_rate\", \"sgst_rate\", \"cess_rate\", \"cess_non_advol_rate\", \"cb_gst_details\", \"igst_amount\", \"cgst_amount\", \"sgst_amount\", \"cess_amount\", \"cess_non_advol_amount\", \"item_weight_details\", \"weight_per_unit\", \"total_weight\", \"column_break_23\", \"weight_uom\", \"warehouse_and_reference\", \"warehouse\", \"prevdoc_doctype\", \"material_request\", \"sales_order\", \"request_for_quotation\", \"col_break4\", \"material_request_item\", \"request_for_quotation_item\", \"item_tax_rate\", \"manufacture_details\", \"manufacturer\", \"column_break_15\", \"manufacturer_part_no\", \"ad_sec_break\", \"cost_center\", \"dimension_col_break\", \"project\", \"section_break_44\", \"page_break\"]"
  }
 ],
 "sync_on_migrate": 1
}